LICENSE
nv/collections/__init__.py
nv/collections/chainsequence/__init__.py
nv/collections/chainsequence/chainlist.py
nv/collections/chainsequence/core.py
nv/collections/mappings/__init__.py
nv/collections/mappings/core.py
nv/collections/mappings/object_dict.py
nv/collections/mappings/standard_key.py
nv/collections/orderedset.py
nv/collections/singletons.py
nv/collections/types.py
nv/collections/utils/__init__.py
nv/collections/utils/nested.py
nv/collections/utils/reprs.py
nv/collections/utils/simple_parser.py
nv/collections/utils/slicer.py
nv_collections-0.1.0.dist-info/LICENSE
nv_collections-0.1.0.dist-info/WHEEL
nv_collections-0.1.0.dist-info/METADATA
nv_collections-0.1.0.dist-info/RECORD
